{
  "1": {
    "enemies": {
      "normal": 5
    },
    "enemies_multiplier": {
      "speed": 1.0,
      "damage": 1.0,
      "health": 1.0
    }
  },
  "2": {
    "enemies": {
      "normal": 4,
      "fast": 2
    },
    "enemies_multiplier": {
      "speed": 1.05,
      "damage": 1.05,
      "health": 1.1
    }
  },
  "3": {
    "enemies": {
      "normal": 5,
      "fast": 3,
      "heavy": 1
    },
    "enemies_multiplier": {
      "speed": 1.1,
      "damage": 1.1,
      "health": 1.15
    }
  },
  "4": {
    "enemies": {
      "normal": 7,
      "fast": 5,
      "heavy": 1
    },
    "enemies_multiplier": {
      "speed": 1.15,
      "damage": 1.15,
      "health": 1.2
    }
  },
  "5": {
    "boss": true,
    "enemies": {
      "first_boss": 1
    },
    "enemies_multiplier": {
      "speed": 1.2,
      "damage": 1.2,
      "health": 1.25
    }
  },
  "6": {
    "enemies": {
      "normal": 11,
      "fast": 9,
      "heavy": 2
    },
    "enemies_multiplier": {
      "speed": 1.3,
      "damage": 1.3,
      "health": 1.3
    }
  },
  "7": {
    "enemies": {
      "normal": 13,
      "fast": 11,
      "heavy": 3
    },
    "enemies_multiplier": {
      "speed": 1.35,
      "damage": 1.35,
      "health": 1.35
    }
  },
  "8": {
    "enemies": {
      "normal": 15,
      "fast": 13,
      "heavy": 3
    },
    "enemies_multiplier": {
      "speed": 1.4,
      "damage": 1.4,
      "health": 1.4
    }
  },
  "9": {
    "enemies": {
      "normal": 17,
      "fast": 15,
      "heavy": 4
    },
    "enemies_multiplier": {
      "speed": 1.45,
      "damage": 1.45,
      "health": 1.5
    }
  },
  "10": {
    "boss": true,
    "enemies": {
      "first_boss": 1
    },
    "enemies_multiplier": {
      "speed": 1.5,
      "damage": 1.5,
      "health": 1.6
    }
  }
}
